kakeibox_serializer_json/__init__.py
kakeibox_serializer_json/serializer/__init__.py
kakeibox_serializer_json/serializer/json_delete_input_serializer.py
kakeibox_serializer_json/serializer/json_serializer.py
kakeibox_serializer_json/serializer/json_update_input_serializer.py
kakeibox_serializer_json-0.2.1.dist-info/AUTHORS.rst
kakeibox_serializer_json-0.2.1.dist-info/LICENSE
kakeibox_serializer_json-0.2.1.dist-info/METADATA
kakeibox_serializer_json-0.2.1.dist-info/WHEEL
kakeibox_serializer_json-0.2.1.dist-info/top_level.txt
kakeibox_serializer_json-0.2.1.dist-info/RECORD
