Metadata-Version: 2.1
Name: kakeibox-serializer-json
Version: 0.2.1
Summary: A package description.
Home-page: https://gitlab.com/kakeibox/kakeibox-cli-app/kakeibox-serializer-json
Author: Jonathan López
Author-email: jlopez@fipasoft.com.mx
License: GNU General Public License v3
Keywords: kakeibox_serializer_json
Platform: UNKNOWN
Classifier: Development Status :: 2 - Pre-Alpha
Classifier: Intended Audience :: Developers
Classifier: License :: OSI Approved :: GNU General Public License v3 (GPLv3)
Classifier: Natural Language :: English
Classifier: Programming Language :: Python :: 3
Classifier: Programming Language :: Python :: 3.4
Classifier: Programming Language :: Python :: 3.5
Classifier: Programming Language :: Python :: 3.6
Classifier: Programming Language :: Python :: 3.7
